ddns_updater/__init__.py
ddns_updater/__main__.py
ddns_updater/constant.py
ddns_updater/db.py
ddns_updater/ddu.py
ddns_updater/models.py
ddns_updater/provider.py
ddns_updater-1.0.1.dist-info/LICENSE
ddns_updater-1.0.1.dist-info/METADATA
ddns_updater-1.0.1.dist-info/WHEEL
ddns_updater-1.0.1.dist-info/entry_points.txt
ddns_updater-1.0.1.dist-info/RECORD
