Metadata-Version: 2.1
Name: ddns-updater
Version: 1.0.1
Summary: Package for updating DynDNS services
License: MIT
Author: Markus Frings
Author-email: coding@frings-mail.de
Requires-Python: >=3.9,<4.0
Classifier: License :: OSI Approved :: MIT License
Classifier: Programming Language :: Python :: 3
Classifier: Programming Language :: Python :: 3.9
Classifier: Programming Language :: Python :: 3.10
Classifier: Programming Language :: Python :: 3.11
Classifier: Programming Language :: Python :: 3.12
Requires-Dist: click (>=8.1.7,<9.0.0)
Requires-Dist: keyring (>=25.0.0,<26.0.0)
Requires-Dist: keyrings-alt (>=5.0.0,<6.0.0)
Requires-Dist: pydantic (>=2.6.4,<3.0.0)
Requires-Dist: requests (>=2.31.0,<3.0.0)
